{
 "generatedAt": "2026-07-19T01:25:22.924Z",
 "disclaimer": "3개년 일봉 종가 기준 단순 재현 통계입니다. 장중 변동성·뉴스·매크로 이벤트는 과거 시점으로 재현할 수 없어 제외했으며, 실제 체결가·슬리피지·거래비용도 반영하지 않았습니다. 과거 승률이 미래 수익을 보장하지 않습니다 — 참고 지표로만 사용하세요.",
 "entryScoreThreshold": 68,
 "perTicker": {
  "005930": {
   "periodStart": "2023-07-17",
   "periodEnd": "2026-07-16",
   "sampleSignals": 234,
   "winRate5d": 55.1,
   "avgReturn5d": 1.82,
   "winRate10d": 63.2,
   "avgReturn10d": 3.56
  },
  "000660": {
   "periodStart": "2023-07-17",
   "periodEnd": "2026-07-16",
   "sampleSignals": 263,
   "winRate5d": 57.8,
   "avgReturn5d": 2.71,
   "winRate10d": 58.6,
   "avgReturn10d": 4.52
  }
 }
}